mysql_to_excel/__init__.py
mysql_to_excel/converter.py
mysql_to_excel-0.1.0.dist-info/LICENSE
mysql_to_excel-0.1.0.dist-info/METADATA
mysql_to_excel-0.1.0.dist-info/WHEEL
mysql_to_excel-0.1.0.dist-info/entry_points.txt
mysql_to_excel-0.1.0.dist-info/top_level.txt
mysql_to_excel-0.1.0.dist-info/RECORD
